_blackfire_profiler.cpython-314-darwin.so
blackfire/LICENSE
blackfire/README.rst
blackfire/VERSION
blackfire/__init__.py
blackfire/__main__.py
blackfire/agent.py
blackfire/apm.py
blackfire/constants.py
blackfire/dyn_sampler.py
blackfire/exceptions.py
blackfire/probe.py
blackfire/profiler.py
blackfire/setup.py
blackfire/utils.py
blackfire/bootstrap/__init__.py
blackfire/bootstrap/sitecustomize.py
blackfire/hooks/__init__.py
blackfire/hooks/utils.py
blackfire/hooks/django/__init__.py
blackfire/hooks/django/middleware.py
blackfire/hooks/django/patch.py
blackfire/hooks/django/utils.py
blackfire/hooks/fastapi/__init__.py
blackfire/hooks/fastapi/middleware.py
blackfire/hooks/fastapi/patch.py
blackfire/hooks/flask/__init__.py
blackfire/hooks/flask/middleware.py
blackfire/hooks/flask/patch.py
blackfire/hooks/nw/__init__.py
blackfire/hooks/nw/patch.py
blackfire/hooks/odoo/__init__.py
blackfire/hooks/odoo/middleware.py
blackfire/hooks/odoo/patch.py
blackfire/hooks/pyramid/__init__.py
blackfire/hooks/pyramid/middleware.py
blackfire/hooks/pyramid/patch.py
blackfire/hooks/requests/__init__.py
blackfire/hooks/requests/patch.py
blackfire/hooks/sys/__init__.py
blackfire/hooks/sys/patch.py
blackfire/hooks/wsgi/__init__.py
blackfire-1.20.37.dist-info/METADATA
blackfire-1.20.37.dist-info/WHEEL
blackfire-1.20.37.dist-info/entry_points.txt
blackfire-1.20.37.dist-info/top_level.txt
blackfire-1.20.37.dist-info/RECORD
